claudeconvo/__init__.py
claudeconvo/__main__.py
claudeconvo/claudeconvo.py
claudeconvo/cli.py
claudeconvo/config.py
claudeconvo/constants.py
claudeconvo/diagnostics.py
claudeconvo/field_mappings.json
claudeconvo/formatters.py
claudeconvo/interactive_setup.py
claudeconvo/options.py
claudeconvo/py.typed
claudeconvo/sample_conversation.jsonl
claudeconvo/session.py
claudeconvo/simple_setup.py
claudeconvo/styles.py
claudeconvo/themes.py
claudeconvo/tool_tracker.py
claudeconvo/utils.py
claudeconvo/parsers/__init__.py
claudeconvo/parsers/adaptive.py
claudeconvo/parsers/registry.py
claudeconvo-0.2.4.dist-info/licenses/LICENSE
claudeconvo-0.2.4.dist-info/METADATA
claudeconvo-0.2.4.dist-info/WHEEL
claudeconvo-0.2.4.dist-info/entry_points.txt
claudeconvo-0.2.4.dist-info/top_level.txt
claudeconvo-0.2.4.dist-info/RECORD
