Metadata-Version: 2.4
Name: claudeconvo
Version: 0.2.4
Summary: View Claude Code session history as a conversation
Author: Lorenzo Pasqualis
Maintainer: Lorenzo Pasqualis
License: MIT
Project-URL: Homepage, https://github.com/lpasqualis/claudeconvo
Project-URL: Documentation, https://github.com/lpasqualis/claudeconvo#readme
Project-URL: Repository, https://github.com/lpasqualis/claudeconvo
Project-URL: Issues, https://github.com/lpasqualis/claudeconvo/issues
Keywords: claude,claude-code,cli,session-viewer,conversation,log-viewer
Classifier: Development Status :: 4 - Beta
Classifier: Environment :: Console
Classifier: Intended Audience :: Developers
Classifier: License :: OSI Approved :: MIT License
Classifier: Operating System :: OS Independent
Classifier: Programming Language :: Python :: 3
Classifier: Programming Language :: Python :: 3.10
Classifier: Programming Language :: Python :: 3.11
Classifier: Programming Language :: Python :: 3.12
Classifier: Topic :: Software Development :: Libraries :: Python Modules
Classifier: Topic :: Utilities
Requires-Python: >=3.10
License-File: LICENSE
Provides-Extra: dev
Requires-Dist: pytest>=7.0; extra == "dev"
Requires-Dist: pytest-cov>=4.0; extra == "dev"
Requires-Dist: ruff>=0.1.0; extra == "dev"
Requires-Dist: mypy>=1.0; extra == "dev"
Requires-Dist: build>=0.10; extra == "dev"
Requires-Dist: twine>=4.0; extra == "dev"
Dynamic: license-file
